LICENSE
MANIFEST.in
README.md
example1.png
example2.png
example5.png
example6.png
pyproject.toml
setup.py
filecraft.egg-info/PKG-INFO
filecraft.egg-info/SOURCES.txt
filecraft.egg-info/dependency_links.txt
filecraft.egg-info/top_level.txt
fileease/__init__.py
fileease/compression.py
fileease/directory_operations.py
fileease/file_operations.py
fileease/image_operations.py
fileease/main.py