Metadata-Version: 2.1
Name: filecraft
Version: 0.0.1
Summary: A comprehensive package to ease the file/folder management
Author: Zack
Classifier: Programming Language :: Python :: 3
Classifier: License :: OSI Approved :: MIT License
Classifier: Operating System :: OS Independent
Requires-Python: >=3.6
License-File: LICENSE
